<?xml version='1.0' encoding='utf-8'?>
<annotation><filename>S0547</filename><size><width>512</width><height>512</height><depth>3</depth></size><object><name>Nasion</name><bndbox><xmin>408</xmin><ymin>134</ymin><xmax>472</xmax><ymax>198</ymax></bndbox></object><object><name>Sella</name><bndbox><xmin>271</xmin><ymin>141</ymin><xmax>335</xmax><ymax>205</ymax></bndbox></object><object><name>Porion</name><bndbox><xmin>228</xmin><ymin>175</ymin><xmax>292</xmax><ymax>239</ymax></bndbox></object><object><name>Orbitale</name><bndbox><xmin>384</xmin><ymin>189</ymin><xmax>448</xmax><ymax>253</ymax></bndbox></object><object><name>Pterygoid</name><bndbox><xmin>304</xmin><ymin>172</ymin><xmax>368</xmax><ymax>236</ymax></bndbox></object><object><name>Basion</name><bndbox><xmin>219</xmin><ymin>217</ymin><xmax>283</xmax><ymax>281</ymax></bndbox></object><object><name>ANS</name><bndbox><xmin>406</xmin><ymin>241</ymin><xmax>470</xmax><ymax>305</ymax></bndbox></object><object><name>PNS</name><bndbox><xmin>301</xmin><ymin>228</ymin><xmax>365</xmax><ymax>292</ymax></bndbox></object><object><name>A point</name><bndbox><xmin>394</xmin><ymin>257</ymin><xmax>458</xmax><ymax>321</ymax></bndbox></object><object><name>B point</name><bndbox><xmin>369</xmin><ymin>344</ymin><xmax>433</xmax><ymax>408</ymax></bndbox></object><object><name>Protuberance menti</name><bndbox><xmin>367</xmin><ymin>359</ymin><xmax>431</xmax><ymax>423</ymax></bndbox></object><object><name>Pogonion</name><bndbox><xmin>365</xmin><ymin>371</ymin><xmax>429</xmax><ymax>435</ymax></bndbox></object><object><name>Menton</name><bndbox><xmin>348</xmin><ymin>384</ymin><xmax>412</xmax><ymax>448</ymax></bndbox></object><object><name>Go-1 Corpuus left</name><bndbox><xmin>258</xmin><ymin>305</ymin><xmax>322</xmax><ymax>369</ymax></bndbox></object><object><name>Go-2 Ramus down</name><bndbox><xmin>246</xmin><ymin>220</ymin><xmax>310</xmax><ymax>284</ymax></bndbox></object><object><name>Articulare</name><bndbox><xmin>243</xmin><ymin>201</ymin><xmax>307</xmax><ymax>265</ymax></bndbox></object><object><name>R3</name><bndbox><xmin>280</xmin><ymin>217</ymin><xmax>344</xmax><ymax>281</ymax></bndbox></object><object><name>R1</name><bndbox><xmin>300</xmin><ymin>261</ymin><xmax>364</xmax><ymax>325</ymax></bndbox></object><object><name>Maxilla 1 crown</name><bndbox><xmin>400</xmin><ymin>308</ymin><xmax>464</xmax><ymax>372</ymax></bndbox></object><object><name>Maxilla 1 root</name><bndbox><xmin>386</xmin><ymin>260</ymin><xmax>450</xmax><ymax>324</ymax></bndbox></object><object><name>Mandible 1 crown</name><bndbox><xmin>394</xmin><ymin>304</ymin><xmax>458</xmax><ymax>368</ymax></bndbox></object><object><name>Mandible 1 root</name><bndbox><xmin>366</xmin><ymin>334</ymin><xmax>430</xmax><ymax>398</ymax></bndbox></object><object><name>Maxilla 6 distal</name><bndbox><xmin>327</xmin><ymin>278</ymin><xmax>391</xmax><ymax>342</ymax></bndbox></object><object><name>Maxilla 6 root</name><bndbox><xmin>340</xmin><ymin>246</ymin><xmax>404</xmax><ymax>310</ymax></bndbox></object><object><name>Mandible 6 distal</name><bndbox><xmin>321</xmin><ymin>286</ymin><xmax>385</xmax><ymax>350</ymax></bndbox></object><object><name>Mandible 6 root</name><bndbox><xmin>309</xmin><ymin>316</ymin><xmax>373</xmax><ymax>380</ymax></bndbox></object><object><name>Glabella</name><bndbox><xmin>430</xmin><ymin>111</ymin><xmax>494</xmax><ymax>175</ymax></bndbox></object><object><name>Soft tissue naison</name><bndbox><xmin>417</xmin><ymin>151</ymin><xmax>481</xmax><ymax>215</ymax></bndbox></object><object><name>Dorsum of nose</name><bndbox><xmin>441</xmin><ymin>210</ymin><xmax>505</xmax><ymax>274</ymax></bndbox></object><object><name>pronasale</name><bndbox><xmin>452</xmin><ymin>233</ymin><xmax>516</xmax><ymax>297</ymax></bndbox></object><object><name>Colunella</name><bndbox><xmin>444</xmin><ymin>250</ymin><xmax>508</xmax><ymax>314</ymax></bndbox></object><object><name>Subnasalle</name><bndbox><xmin>424</xmin><ymin>254</ymin><xmax>488</xmax><ymax>318</ymax></bndbox></object><object><name>Soft tissue A point</name><bndbox><xmin>419</xmin><ymin>263</ymin><xmax>483</xmax><ymax>327</ymax></bndbox></object><object><name>Labrale superius</name><bndbox><xmin>427</xmin><ymin>282</ymin><xmax>491</xmax><ymax>346</ymax></bndbox></object><object><name>Upper lip</name><bndbox><xmin>430</xmin><ymin>293</ymin><xmax>494</xmax><ymax>357</ymax></bndbox></object><object><name>Stms</name><bndbox><xmin>415</xmin><ymin>308</ymin><xmax>479</xmax><ymax>372</ymax></bndbox></object><object><name>Upper embrasure</name><bndbox><xmin>404</xmin><ymin>304</ymin><xmax>468</xmax><ymax>368</ymax></bndbox></object><object><name>Lower embrasure</name><bndbox><xmin>398</xmin><ymin>306</ymin><xmax>462</xmax><ymax>370</ymax></bndbox></object><object><name>Stmi</name><bndbox><xmin>410</xmin><ymin>308</ymin><xmax>474</xmax><ymax>372</ymax></bndbox></object><object><name>Lower lip</name><bndbox><xmin>417</xmin><ymin>323</ymin><xmax>481</xmax><ymax>387</ymax></bndbox></object><object><name>Labial Inferius</name><bndbox><xmin>414</xmin><ymin>331</ymin><xmax>478</xmax><ymax>395</ymax></bndbox></object><object><name>Soft tissue b point</name><bndbox><xmin>399</xmin><ymin>347</ymin><xmax>463</xmax><ymax>411</ymax></bndbox></object><object><name>Soft tissue pogonion</name><bndbox><xmin>400</xmin><ymin>369</ymin><xmax>464</xmax><ymax>433</ymax></bndbox></object><object><name>Soft tissue Gnathion</name><bndbox><xmin>384</xmin><ymin>395</ymin><xmax>448</xmax><ymax>459</ymax></bndbox></object><object><name>Soft tissue Menton</name><bndbox><xmin>356</xmin><ymin>403</ymin><xmax>420</xmax><ymax>467</ymax></bndbox></object><object><name>Cervical point</name><bndbox><xmin>286</xmin><ymin>412</ymin><xmax>350</xmax><ymax>476</ymax></bndbox></object></annotation>